cognilib/__init__.py
cognilib/loss/__init__.py
cognilib/loss/mean_squared_error.py
cognilib/model/__init__.py
cognilib/model/multiple_linear_regression.py
cognilib/model/simple_linear_regression.py
cognilib/preprocessing/__init__.py
cognilib/preprocessing/label_encoder.py
cognilib/utils/__init__.py
cognilib/utils/train_test_split.py
tests/__init__.py
tests/test_MultipleLinearRegression.py
tests/test_label_encoder.py
tests/test_linear_regression.py
tests/test_mean_squared_error.py
tests/test_multiple_linear_regression.py
cognilib-0.1.dist-info/LICENSE
cognilib-0.1.dist-info/METADATA
cognilib-0.1.dist-info/WHEEL
cognilib-0.1.dist-info/top_level.txt
cognilib-0.1.dist-info/RECORD
