Metadata-Version: 2.2
Name: cognilib
Version: 0.1
Summary: A machine learning library
Home-page: https://github.com/armanmaurya/learnix
Author: Arman Maurya
Author-email: armanmarya6@gmail.com
Classifier: Programming Language :: Python :: 3
Classifier: License :: OSI Approved :: MIT License
Classifier: Operating System :: OS Independent
Requires-Python: >=3.6
License-File: LICENSE
Requires-Dist: numpy
Dynamic: author
Dynamic: author-email
Dynamic: classifier
Dynamic: description
Dynamic: description-content-type
Dynamic: home-page
Dynamic: requires-dist
Dynamic: requires-python
Dynamic: summary
